LICENSE
README.md
validoopsie/__init__.py
validoopsie/py.typed
validoopsie/validate.py
validoopsie/validate.pyi
validoopsie/base/__init__.py
validoopsie/base/base_validation.py
validoopsie/base/results_typedict.py
validoopsie/util/__init__.py
validoopsie/util/base_util_functions.py
validoopsie/util/min_max_arg_check.py
validoopsie/util/min_max_filter.py
validoopsie/validation_catalogue/DateValidation/__init__.py
validoopsie/validation_catalogue/DateValidation/column_match_date_format.py
validoopsie/validation_catalogue/DateValidation/date_to_be_between.py
validoopsie/validation_catalogue/EqualityValidation/__init__.py
validoopsie/validation_catalogue/EqualityValidation/pair_column_equality.py
validoopsie/validation_catalogue/NullValidation/__init__.py
validoopsie/validation_catalogue/NullValidation/column_be_null.py
validoopsie/validation_catalogue/NullValidation/column_not_be_null.py
validoopsie/validation_catalogue/StringValidation/__init__.py
validoopsie/validation_catalogue/StringValidation/length_to_be_between.py
validoopsie/validation_catalogue/StringValidation/length_to_be_equal_to.py
validoopsie/validation_catalogue/StringValidation/not_pattern_match.py
validoopsie/validation_catalogue/StringValidation/pattern_match.py
validoopsie/validation_catalogue/TypeValidation/__init__.py
validoopsie/validation_catalogue/TypeValidation/type_check.py
validoopsie/validation_catalogue/UniqueValidation/__init__.py
validoopsie/validation_catalogue/UniqueValidation/column_unique_pair.py
validoopsie/validation_catalogue/UniqueValidation/column_unique_value_count_to_be_between.py
validoopsie/validation_catalogue/UniqueValidation/column_unique_values_to_be_in_list.py
validoopsie/validation_catalogue/ValuesValidation/__init__.py
validoopsie/validation_catalogue/ValuesValidation/column_values_to_be_between.py
validoopsie/validation_catalogue/ValuesValidation/columns_sum_to_be_between.py
validoopsie/validation_catalogue/ValuesValidation/columns_sum_to_be_equal_to.py
validoopsie-1.7.1.dist-info/METADATA
validoopsie-1.7.1.dist-info/WHEEL
validoopsie-1.7.1.dist-info/licenses/LICENSE
validoopsie-1.7.1.dist-info/RECORD
