Metadata-Version: 2.4
Name: Validoopsie
Version: 1.7.1
Summary: Validoopsie is a simple and light data validation library.
Project-URL: Homepage, https://github.com/akmalsoliev/Validoopsie
Project-URL: Issues, https://github.com/akmalsoliev/Validoopsie/issues
Author: Akmal Soliev
License-File: LICENSE
Classifier: License :: OSI Approved :: MIT License
Classifier: Operating System :: OS Independent
Classifier: Programming Language :: Python :: 3
Classifier: Programming Language :: Python :: 3.10
Classifier: Programming Language :: Python :: 3.11
Classifier: Programming Language :: Python :: 3.12
Classifier: Programming Language :: Python :: 3.13
Requires-Python: >=3.10
Requires-Dist: loguru>=0.7.3
Requires-Dist: narwhals>=2.7.0
Requires-Dist: pyarrow>=11.0.0
Requires-Dist: tabulate>=0.9.0
Requires-Dist: typing-extensions>=4.0.0; python_version < '3.11'
